{
  "player_id": "andres-gimenez",
  "mlbam_id": null,
  "full_name": "Andrés Giménez",
  "display_name": "Andrés Giménez",
  "slug": "andres-gimenez",
  "team_abbr": "TOR",
  "team_name": "Toronto Blue Jays",
  "position": "SS",
  "position_group": "Infielder",
  "status": "Active",
  "bats": "L",
  "throws": "R",
  "active": true,
  "hitter_card": {
    "player_id": "andres-gimenez",
    "slug": "andres-gimenez",
    "full_name": "Andrés Giménez",
    "team_abbr": "TOR",
    "position": "SS",
    "games": 66,
    "avg": ".220",
    "obp": ".265",
    "slg": ".353",
    "ops": ".618",
    "hr": 6,
    "rbi": 30,
    "runs": 15,
    "sb": 7,
    "bb": 8,
    "so": 46
  },
  "pitcher_card": null,
  "statcast_hitter_card": {
    "player_id": "andres-gimenez",
    "slug": "andres-gimenez",
    "full_name": "Andrés Giménez",
    "team_abbr": "TOR",
    "avg_exit_velocity": 86.0,
    "max_exit_velocity": 108.9,
    "hard_hit_pct": 24.0,
    "barrel_pct": 3.4,
    "sweet_spot_pct": 26.9,
    "xba": 0.22,
    "xslg": 0.306,
    "xwoba": 0.26
  },
  "generated_at": "2026-06-13T02:26:20Z",
  "metadata": {
    "player_cards_version": "PLAYER-002",
    "sources": [
      "Site Data/players/season_hitter_stats.json",
      "Site Data/players/season_pitcher_stats.json",
      "Site Data/game_cards.json",
      "Site Data/dope-sheet-data.json",
      "Site Data/players/statcast_hitter_cards.json"
    ]
  }
}
