{
  "player_id": "brayan-rocchio",
  "mlbam_id": null,
  "full_name": "Brayan Rocchio",
  "display_name": "Brayan Rocchio",
  "slug": "brayan-rocchio",
  "team_abbr": "CLE",
  "team_name": "Cleveland Guardians",
  "position": "SS",
  "position_group": "Infielder",
  "status": "Active",
  "bats": "S",
  "throws": "R",
  "active": true,
  "hitter_card": {
    "player_id": "brayan-rocchio",
    "slug": "brayan-rocchio",
    "full_name": "Brayan Rocchio",
    "team_abbr": "CLE",
    "position": "SS",
    "games": 67,
    "avg": ".276",
    "obp": ".357",
    "slg": ".396",
    "ops": ".754",
    "hr": 5,
    "rbi": 31,
    "runs": 28,
    "sb": 11,
    "bb": 22,
    "so": 30
  },
  "pitcher_card": null,
  "statcast_hitter_card": {
    "player_id": "brayan-rocchio",
    "slug": "brayan-rocchio",
    "full_name": "Brayan Rocchio",
    "team_abbr": "CLE",
    "avg_exit_velocity": 86.7,
    "max_exit_velocity": 109.6,
    "hard_hit_pct": 32.6,
    "barrel_pct": 3.1,
    "sweet_spot_pct": 32.3,
    "xba": 0.258,
    "xslg": 0.368,
    "xwoba": 0.32
  },
  "generated_at": "2026-06-13T02:26:20Z",
  "metadata": {
    "player_cards_version": "PLAYER-002",
    "sources": [
      "Site Data/players/season_hitter_stats.json",
      "Site Data/players/season_pitcher_stats.json",
      "Site Data/game_cards.json",
      "Site Data/dope-sheet-data.json",
      "Site Data/players/statcast_hitter_cards.json"
    ]
  }
}
