{
  "player_id": "ceddanne-rafaela",
  "mlbam_id": null,
  "full_name": "Ceddanne Rafaela",
  "display_name": "Ceddanne Rafaela",
  "slug": "ceddanne-rafaela",
  "team_abbr": "BOS",
  "team_name": "Boston Red Sox",
  "position": "CF",
  "position_group": "Outfielder",
  "status": "Active",
  "bats": "R",
  "throws": "R",
  "active": true,
  "hitter_card": {
    "player_id": "ceddanne-rafaela",
    "slug": "ceddanne-rafaela",
    "full_name": "Ceddanne Rafaela",
    "team_abbr": "BOS",
    "position": "CF",
    "games": 63,
    "avg": ".280",
    "obp": ".339",
    "slg": ".431",
    "ops": ".770",
    "hr": 6,
    "rbi": 27,
    "runs": 26,
    "sb": 6,
    "bb": 14,
    "so": 51
  },
  "pitcher_card": null,
  "statcast_hitter_card": {
    "player_id": "ceddanne-rafaela",
    "slug": "ceddanne-rafaela",
    "full_name": "Ceddanne Rafaela",
    "team_abbr": "BOS",
    "avg_exit_velocity": 87.3,
    "max_exit_velocity": 108.6,
    "hard_hit_pct": 36.8,
    "barrel_pct": 6.9,
    "sweet_spot_pct": 36.8,
    "xba": 0.243,
    "xslg": 0.363,
    "xwoba": 0.298
  },
  "generated_at": "2026-06-13T02:26:20Z",
  "metadata": {
    "player_cards_version": "PLAYER-002",
    "sources": [
      "Site Data/players/season_hitter_stats.json",
      "Site Data/players/season_pitcher_stats.json",
      "Site Data/game_cards.json",
      "Site Data/dope-sheet-data.json",
      "Site Data/players/statcast_hitter_cards.json"
    ]
  }
}
