{
  "player_id": "chad-stevens",
  "mlbam_id": null,
  "full_name": "Chad Stevens",
  "display_name": "Chad Stevens",
  "slug": "chad-stevens",
  "team_abbr": "COL",
  "team_name": "Colorado Rockies",
  "position": "2B",
  "position_group": "Infielder",
  "status": "Active",
  "bats": "R",
  "throws": "R",
  "active": true,
  "hitter_card": {
    "player_id": "chad-stevens",
    "slug": "chad-stevens",
    "full_name": "Chad Stevens",
    "team_abbr": "COL",
    "position": "2B",
    "games": 14,
    "avg": ".043",
    "obp": ".207",
    "slg": ".043",
    "ops": ".250",
    "hr": 0,
    "rbi": 3,
    "runs": 1,
    "sb": 0,
    "bb": 5,
    "so": 9
  },
  "pitcher_card": null,
  "statcast_hitter_card": null,
  "generated_at": "2026-06-11T04:17:02Z",
  "metadata": {
    "player_cards_version": "PLAYER-002",
    "sources": [
      "Site Data/players/season_hitter_stats.json",
      "Site Data/players/season_pitcher_stats.json",
      "Site Data/game_cards.json",
      "Site Data/dope-sheet-data.json",
      "Site Data/players/statcast_hitter_cards.json"
    ]
  }
}
