{
  "player_id": "david-hamilton",
  "mlbam_id": null,
  "full_name": "David Hamilton",
  "display_name": "David Hamilton",
  "slug": "david-hamilton",
  "team_abbr": "MIL",
  "team_name": "Milwaukee Brewers",
  "position": "SS",
  "position_group": "Infielder",
  "status": "Active",
  "bats": "L",
  "throws": "R",
  "active": true,
  "hitter_card": {
    "player_id": "david-hamilton",
    "slug": "david-hamilton",
    "full_name": "David Hamilton",
    "team_abbr": "MIL",
    "position": "SS",
    "games": 55,
    "avg": ".238",
    "obp": ".326",
    "slg": ".331",
    "ops": ".657",
    "hr": 3,
    "rbi": 11,
    "runs": 29,
    "sb": 14,
    "bb": 20,
    "so": 39
  },
  "pitcher_card": null,
  "statcast_hitter_card": {
    "player_id": "david-hamilton",
    "slug": "david-hamilton",
    "full_name": "David Hamilton",
    "team_abbr": "MIL",
    "avg_exit_velocity": 86.4,
    "max_exit_velocity": 109.9,
    "hard_hit_pct": 29.4,
    "barrel_pct": 3.9,
    "sweet_spot_pct": 25.2,
    "xba": 0.211,
    "xslg": 0.311,
    "xwoba": 0.281
  },
  "generated_at": "2026-06-13T02:26:20Z",
  "metadata": {
    "player_cards_version": "PLAYER-002",
    "sources": [
      "Site Data/players/season_hitter_stats.json",
      "Site Data/players/season_pitcher_stats.json",
      "Site Data/game_cards.json",
      "Site Data/dope-sheet-data.json",
      "Site Data/players/statcast_hitter_cards.json"
    ]
  }
}
