{
  "player_id": "erick-fedde",
  "mlbam_id": null,
  "full_name": "Erick Fedde",
  "display_name": "Erick Fedde",
  "slug": "erick-fedde",
  "team_abbr": "CWS",
  "team_name": "Chicago White Sox",
  "position": "P",
  "position_group": "Pitcher",
  "status": "Active",
  "bats": "R",
  "throws": "R",
  "active": true,
  "hitter_card": null,
  "pitcher_card": {
    "player_id": "erick-fedde",
    "slug": "erick-fedde",
    "full_name": "Erick Fedde",
    "team_abbr": "CWS",
    "position": "P",
    "games": 1,
    "games_started": 1,
    "wins": null,
    "losses": null,
    "saves": null,
    "era": null,
    "ip": "5.0",
    "so": 4,
    "bb": 0,
    "whip": null
  },
  "statcast_hitter_card": null,
  "generated_at": "2026-06-11T03:52:40Z",
  "metadata": {
    "player_cards_version": "PLAYER-002",
    "sources": [
      "Site Data/game_cards.json",
      "Site Data/dope-sheet-data.json",
      "Site Data/players/statcast_hitter_cards.json"
    ]
  }
}
