{
  "player_id": "jake-meyers",
  "mlbam_id": null,
  "full_name": "Jake Meyers",
  "display_name": "Jake Meyers",
  "slug": "jake-meyers",
  "team_abbr": "HOU",
  "team_name": "Houston Astros",
  "position": "CF",
  "position_group": "Outfielder",
  "status": "Active",
  "bats": "R",
  "throws": "L",
  "active": true,
  "hitter_card": {
    "player_id": "jake-meyers",
    "slug": "jake-meyers",
    "full_name": "Jake Meyers",
    "team_abbr": "HOU",
    "position": "CF",
    "games": 32,
    "avg": ".216",
    "obp": ".280",
    "slg": ".320",
    "ops": ".600",
    "hr": 2,
    "rbi": 9,
    "runs": 10,
    "sb": 1,
    "bb": 8,
    "so": 21
  },
  "pitcher_card": null,
  "statcast_hitter_card": null,
  "generated_at": "2026-06-11T04:17:02Z",
  "metadata": {
    "player_cards_version": "PLAYER-002",
    "sources": [
      "Site Data/players/season_hitter_stats.json",
      "Site Data/players/season_pitcher_stats.json",
      "Site Data/game_cards.json",
      "Site Data/dope-sheet-data.json",
      "Site Data/players/statcast_hitter_cards.json"
    ]
  }
}
