{
  "player_id": "luinder-avila",
  "mlbam_id": null,
  "full_name": "Luinder Avila",
  "display_name": "Luinder Avila",
  "slug": "luinder-avila",
  "team_abbr": "KC",
  "team_name": "Kansas City Royals",
  "position": "P",
  "position_group": "Pitcher",
  "status": "Active",
  "bats": "R",
  "throws": "R",
  "active": true,
  "hitter_card": null,
  "pitcher_card": null,
  "statcast_hitter_card": null,
  "generated_at": "2026-06-11T03:52:40Z",
  "metadata": {
    "player_cards_version": "PLAYER-002",
    "sources": [
      "Site Data/game_cards.json",
      "Site Data/dope-sheet-data.json",
      "Site Data/players/statcast_hitter_cards.json"
    ]
  }
}
