{
  "player_id": "michael-mcgreevy",
  "mlbam_id": null,
  "full_name": "Michael McGreevy",
  "display_name": "Michael McGreevy",
  "slug": "michael-mcgreevy",
  "team_abbr": "STL",
  "team_name": "St. Louis Cardinals",
  "position": "P",
  "position_group": "Pitcher",
  "status": "Active",
  "bats": "L",
  "throws": "R",
  "active": true,
  "hitter_card": null,
  "pitcher_card": {
    "player_id": "michael-mcgreevy",
    "slug": "michael-mcgreevy",
    "full_name": "Michael McGreevy",
    "team_abbr": "STL",
    "position": "P",
    "games": 13,
    "games_started": 13,
    "wins": 3,
    "losses": 5,
    "saves": null,
    "era": 2.99,
    "ip": "72.1",
    "so": 49,
    "bb": 17,
    "whip": 1.078
  },
  "statcast_hitter_card": null,
  "generated_at": "2026-06-11T04:17:02Z",
  "metadata": {
    "player_cards_version": "PLAYER-002",
    "sources": [
      "Site Data/players/season_hitter_stats.json",
      "Site Data/players/season_pitcher_stats.json",
      "Site Data/game_cards.json",
      "Site Data/dope-sheet-data.json",
      "Site Data/players/statcast_hitter_cards.json"
    ]
  }
}
