{
  "player_id": "teoscar-hernandez",
  "mlbam_id": null,
  "full_name": "Teoscar Hernández",
  "display_name": "Teoscar Hernández",
  "slug": "teoscar-hernandez",
  "team_abbr": null,
  "team_name": null,
  "position": "LF",
  "position_group": "Outfielder",
  "status": "10-Day IL",
  "bats": null,
  "throws": null,
  "active": true,
  "hitter_card": null,
  "pitcher_card": null,
  "statcast_hitter_card": {
    "player_id": "teoscar-hernandez",
    "slug": "teoscar-hernandez",
    "full_name": "Teoscar Hernández",
    "team_abbr": null,
    "avg_exit_velocity": 89.8,
    "max_exit_velocity": 110.7,
    "hard_hit_pct": null,
    "barrel_pct": 10.9,
    "sweet_spot_pct": null,
    "xba": 0.259,
    "xslg": 0.437,
    "xwoba": 0.339
  },
  "generated_at": "2026-06-11T03:52:40Z",
  "metadata": {
    "player_cards_version": "PLAYER-002",
    "sources": [
      "Site Data/game_cards.json",
      "Site Data/dope-sheet-data.json",
      "Site Data/players/statcast_hitter_cards.json"
    ]
  }
}
