{
  "player_id": "trey-yesavage",
  "mlbam_id": null,
  "full_name": "Trey Yesavage",
  "display_name": "Trey Yesavage",
  "slug": "trey-yesavage",
  "team_abbr": "TOR",
  "team_name": "Toronto Blue Jays",
  "position": "P",
  "position_group": "Pitcher",
  "status": "Active",
  "bats": "R",
  "throws": "R",
  "active": true,
  "hitter_card": null,
  "pitcher_card": {
    "player_id": "trey-yesavage",
    "slug": "trey-yesavage",
    "full_name": "Trey Yesavage",
    "team_abbr": "TOR",
    "position": "P",
    "games": 8,
    "games_started": 8,
    "wins": 2,
    "losses": 3,
    "saves": null,
    "era": 3.16,
    "ip": "42.2",
    "so": 44,
    "bb": 19,
    "whip": 1.172
  },
  "statcast_hitter_card": null,
  "generated_at": "2026-06-11T04:17:02Z",
  "metadata": {
    "player_cards_version": "PLAYER-002",
    "sources": [
      "Site Data/players/season_hitter_stats.json",
      "Site Data/players/season_pitcher_stats.json",
      "Site Data/game_cards.json",
      "Site Data/dope-sheet-data.json",
      "Site Data/players/statcast_hitter_cards.json"
    ]
  }
}
