{
  "player_id": "will-benson",
  "mlbam_id": null,
  "full_name": "Will Benson",
  "display_name": "Will Benson",
  "slug": "will-benson",
  "team_abbr": "CIN",
  "team_name": "Cincinnati Reds",
  "position": "RF",
  "position_group": "Outfielder",
  "status": "Active",
  "bats": "L",
  "throws": "L",
  "active": true,
  "hitter_card": null,
  "pitcher_card": null,
  "generated_at": "2026-06-11T03:08:49Z",
  "metadata": {
    "player_cards_version": "PLAYER-002",
    "sources": [
      "Site Data/game_cards.json",
      "Site Data/dope-sheet-data.json"
    ]
  }
}
