{
  "player_id": "wyatt-langford",
  "mlbam_id": null,
  "full_name": "Wyatt Langford",
  "display_name": "Wyatt Langford",
  "slug": "wyatt-langford",
  "team_abbr": "TEX",
  "team_name": "Texas Rangers",
  "position": "LF",
  "position_group": "Outfielder",
  "status": "Active",
  "bats": "R",
  "throws": "R",
  "active": true,
  "hitter_card": {
    "player_id": "wyatt-langford",
    "slug": "wyatt-langford",
    "full_name": "Wyatt Langford",
    "team_abbr": "TEX",
    "position": "LF",
    "games": 24,
    "avg": ".226",
    "obp": ".273",
    "slg": ".376",
    "ops": ".649",
    "hr": 2,
    "rbi": 5,
    "runs": 12,
    "sb": 3,
    "bb": 6,
    "so": 23
  },
  "pitcher_card": null,
  "statcast_hitter_card": null,
  "generated_at": "2026-06-11T04:17:02Z",
  "metadata": {
    "player_cards_version": "PLAYER-002",
    "sources": [
      "Site Data/players/season_hitter_stats.json",
      "Site Data/players/season_pitcher_stats.json",
      "Site Data/game_cards.json",
      "Site Data/dope-sheet-data.json",
      "Site Data/players/statcast_hitter_cards.json"
    ]
  }
}
