{
  "date": "2026-06-25",
  "meta": {
    "generated_at": "2026-06-26T00:01:20Z",
    "date": "2026-06-25",
    "season": 2026,
    "source": "Barrel Proof player signal stack",
    "status": "success",
    "game_count": 9
  },
  "games": [
    {
      "game_id": "822961",
      "game_date": "2026-06-25",
      "away_team": "KC",
      "home_team": "TB",
      "away_team_name": "Kansas City Royals",
      "home_team_name": "Tampa Bay Rays",
      "venue": null,
      "lineup_source": "confirmed_lineup",
      "away_lineup_source": "confirmed_lineup",
      "home_lineup_source": "confirmed_lineup",
      "probable_pitchers": {
        "away": {
          "slug": "seth-lugo",
          "full_name": "Seth Lugo",
          "team_abbr": "KC",
          "throws": null,
          "pitcher_foundation_signal": 44,
          "profile_type": "Volatile Arm",
          "confidence": "HIGH",
          "k9": 7.58,
          "bb9": 2.84,
          "era": 3.91,
          "whip": 1.355
        },
        "home": {
          "slug": "casey-legumina",
          "full_name": "Casey Legumina",
          "team_abbr": "TB",
          "throws": null,
          "pitcher_foundation_signal": 55,
          "profile_type": "Volatile Arm",
          "confidence": "MEDIUM",
          "k9": 6.83,
          "bb9": 1.86,
          "era": 3.1,
          "whip": 1.276
        }
      },
      "away_bats_to_watch": [
        {
          "slug": "jac-caglianone",
          "full_name": "Jac Caglianone",
          "team_abbr": "KC",
          "position": "RF",
          "bats": "L",
          "power_signal": 93,
          "contact_signal": 58,
          "luck_gap_points": 10,
          "hitter_profile_type": "Real Power Bat",
          "confidence": "HIGH",
          "tags": [
            "Power Watch",
            "DFS Watch"
          ],
          "note": "Jac Caglianone brings strong power indicators."
        }
      ],
      "home_bats_to_watch": [
        {
          "slug": "junior-caminero",
          "full_name": "Junior Caminero",
          "team_abbr": "TB",
          "position": "3B",
          "bats": "R",
          "power_signal": 85,
          "contact_signal": 85,
          "luck_gap_points": -9,
          "hitter_profile_type": "Real Power Bat",
          "confidence": "HIGH",
          "tags": [
            "Power Watch",
            "Contact Edge",
            "DFS Watch"
          ],
          "note": "Junior Caminero brings strong power indicators, and backed by a stable contact profile."
        },
        {
          "slug": "jonathan-aranda",
          "full_name": "Jonathan Aranda",
          "team_abbr": "TB",
          "position": "1B",
          "bats": "L",
          "power_signal": 75,
          "contact_signal": 69,
          "luck_gap_points": 11,
          "hitter_profile_type": "Real Power Bat",
          "confidence": "HIGH",
          "tags": [
            "Power Watch"
          ],
          "note": "Jonathan Aranda brings strong power indicators."
        },
        {
          "slug": "yandy-diaz",
          "full_name": "Yandy D\u00edaz",
          "team_abbr": "TB",
          "position": "DH",
          "bats": "R",
          "power_signal": 70,
          "contact_signal": 87,
          "luck_gap_points": -32,
          "hitter_profile_type": "Watch List",
          "confidence": "HIGH",
          "tags": [
            "Contact Edge",
            "DFS Watch"
          ],
          "note": "Yandy D\u00edaz backed by a stable contact profile."
        }
      ],
      "away_lineup_pressure": {
        "power_score": 93,
        "contact_score": 58,
        "profile": "Power-heavy pressure",
        "notes": []
      },
      "home_lineup_pressure": {
        "power_score": 77,
        "contact_score": 80,
        "profile": "Heavy lineup pressure",
        "notes": [
          "Multiple high-signal bats are clustered in this lineup: Junior Caminero, Yandy D\u00edaz."
        ]
      },
      "pitcher_edges": [],
      "fantasy_watch": [
        "Power Watch: Jac Caglianone is a home run threat in today's matchup.",
        "Power Watch: Junior Caminero is a home run threat in today's matchup.",
        "DFS Stacks: Multiple high-signal bats are clustered in this lineup: Junior Caminero, Yandy D\u00edaz."
      ],
      "matchup_notes": [
        "Seth Lugo (Volatile Arm) faces Casey Legumina (Volatile Arm)."
      ]
    },
    {
      "game_id": "823366",
      "game_date": "2026-06-25",
      "away_team": "SEA",
      "home_team": "PIT",
      "away_team_name": "Seattle Mariners",
      "home_team_name": "Pittsburgh Pirates",
      "venue": null,
      "lineup_source": "confirmed_lineup",
      "away_lineup_source": "confirmed_lineup",
      "home_lineup_source": "confirmed_lineup",
      "probable_pitchers": {
        "away": {
          "slug": "bryce-miller",
          "full_name": "Bryce Miller",
          "team_abbr": "SEA",
          "throws": null,
          "pitcher_foundation_signal": 90,
          "profile_type": "Strong Foundation",
          "confidence": "MEDIUM",
          "k9": 9.67,
          "bb9": 1.67,
          "era": 1.33,
          "whip": 0.778
        },
        "home": {
          "slug": "bubba-chandler",
          "full_name": "Bubba Chandler",
          "team_abbr": "PIT",
          "throws": null,
          "pitcher_foundation_signal": 27,
          "profile_type": "Pitching Risk",
          "confidence": "HIGH",
          "k9": 8.95,
          "bb9": 5.78,
          "era": 4.91,
          "whip": 1.444
        }
      },
      "away_bats_to_watch": [
        {
          "slug": "randy-arozarena",
          "full_name": "Randy Arozarena",
          "team_abbr": "SEA",
          "position": "LF",
          "bats": "R",
          "power_signal": 64,
          "contact_signal": 70,
          "luck_gap_points": -13,
          "hitter_profile_type": "Balanced Producer",
          "confidence": "HIGH",
          "tags": [
            "Balanced Producer"
          ],
          "note": "Randy Arozarena profile flagged for today's matchup."
        },
        {
          "slug": "luke-raley",
          "full_name": "Luke Raley",
          "team_abbr": "SEA",
          "position": "RF",
          "bats": "L",
          "power_signal": 87,
          "contact_signal": 39,
          "luck_gap_points": 11,
          "hitter_profile_type": "Volatile Slugger",
          "confidence": "HIGH",
          "tags": [
            "Power Watch",
            "DFS Watch"
          ],
          "note": "Luke Raley brings strong power indicators."
        },
        {
          "slug": "cal-raleigh",
          "full_name": "Cal Raleigh",
          "team_abbr": "SEA",
          "position": "C",
          "bats": null,
          "power_signal": 51,
          "contact_signal": 11,
          "luck_gap_points": 37,
          "hitter_profile_type": "Watch List",
          "confidence": "HIGH",
          "tags": [
            "DFS Watch"
          ],
          "note": "Cal Raleigh expected production is running ahead of current results."
        }
      ],
      "home_bats_to_watch": [
        {
          "slug": "bryan-reynolds",
          "full_name": "Bryan Reynolds",
          "team_abbr": "PIT",
          "position": "LF",
          "bats": "S",
          "power_signal": 68,
          "contact_signal": 73,
          "luck_gap_points": 2,
          "hitter_profile_type": "Balanced Producer",
          "confidence": "HIGH",
          "tags": [
            "Balanced Producer"
          ],
          "note": "Bryan Reynolds profile flagged for today's matchup."
        }
      ],
      "away_lineup_pressure": {
        "power_score": 67,
        "contact_score": 40,
        "profile": "Moderate lineup pressure",
        "notes": [
          "Multiple high-signal bats are clustered in this lineup: Luke Raley, Cal Raleigh."
        ]
      },
      "home_lineup_pressure": {
        "power_score": 68,
        "contact_score": 73,
        "profile": "Moderate lineup pressure",
        "notes": []
      },
      "pitcher_edges": [
        {
          "pitcher_slug": "bryce-miller",
          "pitcher_name": "Bryce Miller",
          "team_abbr": "SEA",
          "opponent_team": "PIT",
          "edge_type": "Strikeout Upside",
          "confidence": "MEDIUM",
          "pitcher_foundation_signal": 90,
          "pitcher_profile_type": "Strong Foundation",
          "k9": 9.67,
          "bb9": 1.67,
          "note": "Bryce Miller has strikeout upside against PIT."
        },
        {
          "pitcher_slug": "bryce-miller",
          "pitcher_name": "Bryce Miller",
          "team_abbr": "SEA",
          "opponent_team": "PIT",
          "edge_type": "Starting-Pitching Edge",
          "confidence": "MEDIUM",
          "pitcher_foundation_signal": 90,
          "pitcher_profile_type": "Strong Foundation",
          "k9": 9.67,
          "bb9": 1.67,
          "note": "Bryce Miller gives his team the stronger starting-pitching edge in this matchup."
        },
        {
          "pitcher_slug": "bubba-chandler",
          "pitcher_name": "Bubba Chandler",
          "team_abbr": "PIT",
          "opponent_team": "SEA",
          "edge_type": "Pitcher Risk",
          "confidence": "HIGH",
          "pitcher_foundation_signal": 27,
          "pitcher_profile_type": "Pitching Risk",
          "k9": 8.95,
          "bb9": 5.78,
          "note": "Bubba Chandler is a risky spot against SEA."
        }
      ],
      "fantasy_watch": [
        "Power Watch: Luke Raley is a home run threat in today's matchup.",
        "Strikeout Upside: Bryce Miller has strikeout upside today.",
        "Risk Spot: Bubba Chandler is a risky spot against SEA."
      ],
      "matchup_notes": [
        "Bryce Miller (Strong Foundation) faces Bubba Chandler (Pitching Risk)."
      ]
    },
    {
      "game_id": "823209",
      "game_date": "2026-06-25",
      "away_team": "ATH",
      "home_team": "SF",
      "away_team_name": "Oakland Athletics",
      "home_team_name": "San Francisco Giants",
      "venue": null,
      "lineup_source": "confirmed_lineup",
      "away_lineup_source": "confirmed_lineup",
      "home_lineup_source": "confirmed_lineup",
      "probable_pitchers": {
        "away": {
          "slug": "jeffrey-springs",
          "full_name": "Jeffrey Springs",
          "team_abbr": "ATH",
          "throws": null,
          "pitcher_foundation_signal": 41,
          "profile_type": "Volatile Arm",
          "confidence": "HIGH",
          "k9": 7.56,
          "bb9": 2.76,
          "era": 4.68,
          "whip": 1.293
        },
        "home": {
          "slug": "landen-roupp",
          "full_name": "Landen Roupp",
          "team_abbr": "SF",
          "throws": null,
          "pitcher_foundation_signal": 52,
          "profile_type": "Volatile Arm",
          "confidence": "HIGH",
          "k9": 9.95,
          "bb9": 3.88,
          "era": 4.0,
          "whip": 1.292
        }
      },
      "away_bats_to_watch": [
        {
          "slug": "nick-kurtz",
          "full_name": "Nick Kurtz",
          "team_abbr": "ATH",
          "position": "1B",
          "bats": "L",
          "power_signal": 96,
          "contact_signal": 69,
          "luck_gap_points": -19,
          "hitter_profile_type": "Real Power Bat",
          "confidence": "HIGH",
          "tags": [
            "Power Watch",
            "DFS Watch"
          ],
          "note": "Nick Kurtz brings strong power indicators."
        },
        {
          "slug": "shea-langeliers",
          "full_name": "Shea Langeliers",
          "team_abbr": "ATH",
          "position": "C",
          "bats": "R",
          "power_signal": 89,
          "contact_signal": 69,
          "luck_gap_points": -3,
          "hitter_profile_type": "Real Power Bat",
          "confidence": "HIGH",
          "tags": [
            "Power Watch",
            "DFS Watch"
          ],
          "note": "Shea Langeliers brings strong power indicators."
        },
        {
          "slug": "tyler-soderstrom",
          "full_name": "Tyler Soderstrom",
          "team_abbr": "ATH",
          "position": "LF",
          "bats": "L",
          "power_signal": 68,
          "contact_signal": 62,
          "luck_gap_points": -9,
          "hitter_profile_type": "Balanced Producer",
          "confidence": "HIGH",
          "tags": [
            "Balanced Producer"
          ],
          "note": "Tyler Soderstrom profile flagged for today's matchup."
        },
        {
          "slug": "lawrence-butler",
          "full_name": "Lawrence Butler",
          "team_abbr": "ATH",
          "position": "RF",
          "bats": "L",
          "power_signal": 43,
          "contact_signal": 27,
          "luck_gap_points": 73,
          "hitter_profile_type": "Watch List",
          "confidence": "HIGH",
          "tags": [
            "DFS Watch"
          ],
          "note": "Lawrence Butler expected production is running ahead of current results."
        }
      ],
      "home_bats_to_watch": [
        {
          "slug": "jung-hoo-lee",
          "full_name": "Jung Hoo Lee",
          "team_abbr": "SF",
          "position": "RF",
          "bats": "L",
          "power_signal": 23,
          "contact_signal": 80,
          "luck_gap_points": -25,
          "hitter_profile_type": "Contact-First Bat",
          "confidence": "HIGH",
          "tags": [
            "Contact Edge"
          ],
          "note": "Jung Hoo Lee backed by a stable contact profile."
        }
      ],
      "away_lineup_pressure": {
        "power_score": 74,
        "contact_score": 57,
        "profile": "Moderate lineup pressure",
        "notes": [
          "Multiple high-signal bats are clustered in this lineup: Nick Kurtz, Shea Langeliers, Lawrence Butler."
        ]
      },
      "home_lineup_pressure": {
        "power_score": 23,
        "contact_score": 80,
        "profile": "Contact-heavy pressure",
        "notes": []
      },
      "pitcher_edges": [],
      "fantasy_watch": [
        "Power Watch: Nick Kurtz is a home run threat in today's matchup."
      ],
      "matchup_notes": [
        "Jeffrey Springs (Volatile Arm) faces Landen Roupp (Volatile Arm)."
      ]
    },
    {
      "game_id": "824258",
      "game_date": "2026-06-25",
      "away_team": "HOU",
      "home_team": "DET",
      "away_team_name": "Houston Astros",
      "home_team_name": "Detroit Tigers",
      "venue": null,
      "lineup_source": "confirmed_lineup",
      "away_lineup_source": "confirmed_lineup",
      "home_lineup_source": "confirmed_lineup",
      "probable_pitchers": {
        "away": {
          "slug": "tatsuya-imai",
          "full_name": "Tatsuya Imai",
          "team_abbr": "HOU",
          "throws": null,
          "pitcher_foundation_signal": 29,
          "profile_type": "Pitching Risk",
          "confidence": "MEDIUM",
          "k9": 9.44,
          "bb9": 6.03,
          "era": 5.24,
          "whip": 1.398
        },
        "home": {
          "slug": "troy-melton",
          "full_name": "Troy Melton",
          "team_abbr": "DET",
          "throws": null,
          "pitcher_foundation_signal": 58,
          "profile_type": "Volatile Arm",
          "confidence": "MEDIUM",
          "k9": 4.91,
          "bb9": 2.1,
          "era": 2.81,
          "whip": 1.013
        }
      },
      "away_bats_to_watch": [
        {
          "slug": "yordan-alvarez",
          "full_name": "Yordan Alvarez",
          "team_abbr": "HOU",
          "position": "DH",
          "bats": "L",
          "power_signal": 98,
          "contact_signal": 93,
          "luck_gap_points": 42,
          "hitter_profile_type": "Buy-Low Bat",
          "confidence": "HIGH",
          "tags": [
            "Power Watch",
            "Contact Edge",
            "Buy-Low Bat",
            "DFS Watch"
          ],
          "note": "Yordan Alvarez brings strong power indicators, and backed by a stable contact profile, and expected production is running ahead of current results."
        },
        {
          "slug": "cam-smith",
          "full_name": "Cam Smith",
          "team_abbr": "HOU",
          "position": "RF",
          "bats": "R",
          "power_signal": 73,
          "contact_signal": 36,
          "luck_gap_points": 36,
          "hitter_profile_type": "Buy-Low Bat",
          "confidence": "HIGH",
          "tags": [
            "Buy-Low Bat",
            "DFS Watch"
          ],
          "note": "Cam Smith expected production is running ahead of current results."
        }
      ],
      "home_bats_to_watch": [
        {
          "slug": "dillon-dingler",
          "full_name": "Dillon Dingler",
          "team_abbr": "DET",
          "position": "C",
          "bats": "R",
          "power_signal": 81,
          "contact_signal": 68,
          "luck_gap_points": 36,
          "hitter_profile_type": "Buy-Low Bat",
          "confidence": "HIGH",
          "tags": [
            "Power Watch",
            "Buy-Low Bat",
            "DFS Watch"
          ],
          "note": "Dillon Dingler brings strong power indicators, and expected production is running ahead of current results."
        },
        {
          "slug": "riley-greene",
          "full_name": "Riley Greene",
          "team_abbr": "DET",
          "position": "LF",
          "bats": "L",
          "power_signal": 80,
          "contact_signal": 68,
          "luck_gap_points": -9,
          "hitter_profile_type": "Real Power Bat",
          "confidence": "HIGH",
          "tags": [
            "Power Watch"
          ],
          "note": "Riley Greene brings strong power indicators."
        },
        {
          "slug": "kevin-mcgonigle",
          "full_name": "Kevin McGonigle",
          "team_abbr": "DET",
          "position": "SS",
          "bats": "L",
          "power_signal": 50,
          "contact_signal": 87,
          "luck_gap_points": 10,
          "hitter_profile_type": "Contact-First Bat",
          "confidence": "HIGH",
          "tags": [
            "Contact Edge",
            "DFS Watch"
          ],
          "note": "Kevin McGonigle backed by a stable contact profile."
        }
      ],
      "away_lineup_pressure": {
        "power_score": 86,
        "contact_score": 64,
        "profile": "Power-heavy pressure",
        "notes": [
          "Multiple high-signal bats are clustered in this lineup: Yordan Alvarez, Cam Smith."
        ]
      },
      "home_lineup_pressure": {
        "power_score": 70,
        "contact_score": 74,
        "profile": "Moderate lineup pressure",
        "notes": [
          "Multiple high-signal bats are clustered in this lineup: Dillon Dingler, Kevin McGonigle."
        ]
      },
      "pitcher_edges": [
        {
          "pitcher_slug": "tatsuya-imai",
          "pitcher_name": "Tatsuya Imai",
          "team_abbr": "HOU",
          "opponent_team": "DET",
          "edge_type": "Pitcher Risk",
          "confidence": "MEDIUM",
          "pitcher_foundation_signal": 29,
          "pitcher_profile_type": "Pitching Risk",
          "k9": 9.44,
          "bb9": 6.03,
          "note": "Tatsuya Imai is a risky spot against DET."
        }
      ],
      "fantasy_watch": [
        "Power Watch: Yordan Alvarez is a home run threat in today's matchup.",
        "Power Watch: Dillon Dingler is a home run threat in today's matchup.",
        "Risk Spot: Tatsuya Imai is a risky spot against DET.",
        "Buy-Low Bat: Yordan Alvarez has been better than his results show.",
        "Buy-Low Bat: Dillon Dingler has been better than his results show."
      ],
      "matchup_notes": [
        "Tatsuya Imai (Pitching Risk) faces Troy Melton (Volatile Arm)."
      ]
    },
    {
      "game_id": "822717",
      "game_date": "2026-06-25",
      "away_team": "PHI",
      "home_team": "WSH",
      "away_team_name": "Philadelphia Phillies",
      "home_team_name": "Washington Nationals",
      "venue": null,
      "lineup_source": "confirmed_lineup",
      "away_lineup_source": "confirmed_lineup",
      "home_lineup_source": "confirmed_lineup",
      "probable_pitchers": {
        "away": {
          "slug": "cristopher-sanchez",
          "full_name": "Cristopher S\u00e1nchez",
          "team_abbr": "PHI",
          "throws": null,
          "pitcher_foundation_signal": 90,
          "profile_type": "Ace Foundation",
          "confidence": "HIGH",
          "k9": 10.9,
          "bb9": 1.74,
          "era": 1.54,
          "whip": 1.061
        },
        "home": {
          "slug": "cade-cavalli",
          "full_name": "Cade Cavalli",
          "team_abbr": "WSH",
          "throws": null,
          "pitcher_foundation_signal": 51,
          "profile_type": "Volatile Arm",
          "confidence": "HIGH",
          "k9": 9.82,
          "bb9": 3.23,
          "era": 3.88,
          "whip": 1.435
        }
      },
      "away_bats_to_watch": [
        {
          "slug": "bryce-harper",
          "full_name": "Bryce Harper",
          "team_abbr": "PHI",
          "position": "1B",
          "bats": "L",
          "power_signal": 82,
          "contact_signal": 87,
          "luck_gap_points": 29,
          "hitter_profile_type": "Real Power Bat",
          "confidence": "HIGH",
          "tags": [
            "Power Watch",
            "Contact Edge",
            "DFS Watch"
          ],
          "note": "Bryce Harper brings strong power indicators, and backed by a stable contact profile."
        },
        {
          "slug": "kyle-schwarber",
          "full_name": "Kyle Schwarber",
          "team_abbr": "PHI",
          "position": "DH",
          "bats": "L",
          "power_signal": 95,
          "contact_signal": 54,
          "luck_gap_points": -20,
          "hitter_profile_type": "Volatile Slugger",
          "confidence": "HIGH",
          "tags": [
            "Power Watch",
            "DFS Watch"
          ],
          "note": "Kyle Schwarber brings strong power indicators."
        },
        {
          "slug": "jt-realmuto",
          "full_name": "J.T. Realmuto",
          "team_abbr": "PHI",
          "position": "C",
          "bats": "R",
          "power_signal": 28,
          "contact_signal": 35,
          "luck_gap_points": 52,
          "hitter_profile_type": "Watch List",
          "confidence": "HIGH",
          "tags": [
            "DFS Watch"
          ],
          "note": "J.T. Realmuto expected production is running ahead of current results."
        }
      ],
      "home_bats_to_watch": [
        {
          "slug": "james-wood",
          "full_name": "James Wood",
          "team_abbr": "WSH",
          "position": "RF",
          "bats": "L",
          "power_signal": 99,
          "contact_signal": 76,
          "luck_gap_points": 27,
          "hitter_profile_type": "Real Power Bat",
          "confidence": "HIGH",
          "tags": [
            "Power Watch",
            "Contact Edge",
            "DFS Watch"
          ],
          "note": "James Wood brings strong power indicators, and backed by a stable contact profile."
        },
        {
          "slug": "curtis-mead",
          "full_name": "Curtis Mead",
          "team_abbr": "WSH",
          "position": "1B",
          "bats": "R",
          "power_signal": 64,
          "contact_signal": 75,
          "luck_gap_points": 6,
          "hitter_profile_type": "Balanced Producer",
          "confidence": "HIGH",
          "tags": [
            "Contact Edge",
            "Balanced Producer"
          ],
          "note": "Curtis Mead backed by a stable contact profile."
        }
      ],
      "away_lineup_pressure": {
        "power_score": 68,
        "contact_score": 59,
        "profile": "Moderate lineup pressure",
        "notes": [
          "Multiple high-signal bats are clustered in this lineup: Bryce Harper, Kyle Schwarber, J.T. Realmuto."
        ]
      },
      "home_lineup_pressure": {
        "power_score": 82,
        "contact_score": 76,
        "profile": "Heavy lineup pressure",
        "notes": []
      },
      "pitcher_edges": [
        {
          "pitcher_slug": "cristopher-sanchez",
          "pitcher_name": "Cristopher S\u00e1nchez",
          "team_abbr": "PHI",
          "opponent_team": "WSH",
          "edge_type": "Strikeout Upside",
          "confidence": "HIGH",
          "pitcher_foundation_signal": 90,
          "pitcher_profile_type": "Ace Foundation",
          "k9": 10.9,
          "bb9": 1.74,
          "note": "Cristopher S\u00e1nchez has strikeout upside against WSH."
        },
        {
          "pitcher_slug": "cristopher-sanchez",
          "pitcher_name": "Cristopher S\u00e1nchez",
          "team_abbr": "PHI",
          "opponent_team": "WSH",
          "edge_type": "Starting-Pitching Edge",
          "confidence": "HIGH",
          "pitcher_foundation_signal": 90,
          "pitcher_profile_type": "Ace Foundation",
          "k9": 10.9,
          "bb9": 1.74,
          "note": "Cristopher S\u00e1nchez gives his team the stronger starting-pitching edge in this matchup."
        }
      ],
      "fantasy_watch": [
        "Power Watch: Bryce Harper is a home run threat in today's matchup.",
        "Power Watch: James Wood is a home run threat in today's matchup.",
        "Strikeout Upside: Cristopher S\u00e1nchez has strikeout upside today.",
        "Risk Spot: Heavy lineup pressure lineup faces a tough matchup in Cristopher S\u00e1nchez."
      ],
      "matchup_notes": [
        "Cristopher S\u00e1nchez (Ace Foundation) faces Cade Cavalli (Volatile Arm)."
      ]
    },
    {
      "game_id": "822797",
      "game_date": "2026-06-25",
      "away_team": "TEX",
      "home_team": "TOR",
      "away_team_name": "Texas Rangers",
      "home_team_name": "Toronto Blue Jays",
      "venue": null,
      "lineup_source": "confirmed_lineup",
      "away_lineup_source": "confirmed_lineup",
      "home_lineup_source": "confirmed_lineup",
      "probable_pitchers": {
        "away": {
          "slug": "mackenzie-gore",
          "full_name": "MacKenzie Gore",
          "team_abbr": "TEX",
          "throws": null,
          "pitcher_foundation_signal": 46,
          "profile_type": "Volatile Arm",
          "confidence": "HIGH",
          "k9": 9.55,
          "bb9": 4.09,
          "era": 4.23,
          "whip": 1.288
        },
        "home": {
          "slug": "kevin-gausman",
          "full_name": "Kevin Gausman",
          "team_abbr": "TOR",
          "throws": null,
          "pitcher_foundation_signal": 69,
          "profile_type": "Stable Arm",
          "confidence": "HIGH",
          "k9": 8.89,
          "bb9": 1.57,
          "era": 3.6,
          "whip": 1.088
        }
      },
      "away_bats_to_watch": [
        {
          "slug": "brandon-nimmo",
          "full_name": "Brandon Nimmo",
          "team_abbr": "TEX",
          "position": "RF",
          "bats": "L",
          "power_signal": 74,
          "contact_signal": 61,
          "luck_gap_points": 53,
          "hitter_profile_type": "Buy-Low Bat",
          "confidence": "HIGH",
          "tags": [
            "Buy-Low Bat",
            "DFS Watch"
          ],
          "note": "Brandon Nimmo expected production is running ahead of current results."
        },
        {
          "slug": "corey-seager",
          "full_name": "Corey Seager",
          "team_abbr": "TEX",
          "position": "SS",
          "bats": "L",
          "power_signal": 80,
          "contact_signal": 27,
          "luck_gap_points": 53,
          "hitter_profile_type": "Buy-Low Bat",
          "confidence": "HIGH",
          "tags": [
            "Power Watch",
            "Buy-Low Bat",
            "DFS Watch"
          ],
          "note": "Corey Seager brings strong power indicators, and expected production is running ahead of current results."
        },
        {
          "slug": "joc-pederson",
          "full_name": "Joc Pederson",
          "team_abbr": "TEX",
          "position": "DH",
          "bats": "L",
          "power_signal": 66,
          "contact_signal": 64,
          "luck_gap_points": 7,
          "hitter_profile_type": "Balanced Producer",
          "confidence": "HIGH",
          "tags": [
            "Balanced Producer"
          ],
          "note": "Joc Pederson profile flagged for today's matchup."
        }
      ],
      "home_bats_to_watch": [
        {
          "slug": "vladimir-guerrero-jr",
          "full_name": "Vladimir Guerrero Jr.",
          "team_abbr": "TOR",
          "position": "1B",
          "bats": "R",
          "power_signal": 58,
          "contact_signal": 86,
          "luck_gap_points": 31,
          "hitter_profile_type": "Contact-First Bat",
          "confidence": "HIGH",
          "tags": [
            "Contact Edge",
            "DFS Watch"
          ],
          "note": "Vladimir Guerrero Jr. backed by a stable contact profile."
        },
        {
          "slug": "kazuma-okamoto",
          "full_name": "Kazuma Okamoto",
          "team_abbr": "TOR",
          "position": "3B",
          "bats": "R",
          "power_signal": 83,
          "contact_signal": 28,
          "luck_gap_points": 1,
          "hitter_profile_type": "Volatile Slugger",
          "confidence": "HIGH",
          "tags": [
            "Power Watch"
          ],
          "note": "Kazuma Okamoto brings strong power indicators."
        }
      ],
      "away_lineup_pressure": {
        "power_score": 73,
        "contact_score": 51,
        "profile": "Moderate lineup pressure",
        "notes": [
          "Multiple high-signal bats are clustered in this lineup: Brandon Nimmo, Corey Seager."
        ]
      },
      "home_lineup_pressure": {
        "power_score": 70,
        "contact_score": 57,
        "profile": "Moderate lineup pressure",
        "notes": []
      },
      "pitcher_edges": [],
      "fantasy_watch": [
        "Power Watch: Corey Seager is a home run threat in today's matchup.",
        "Power Watch: Kazuma Okamoto is a home run threat in today's matchup.",
        "Buy-Low Bat: Brandon Nimmo has been better than his results show."
      ],
      "matchup_notes": [
        "MacKenzie Gore (Volatile Arm) faces Kevin Gausman (Stable Arm)."
      ]
    },
    {
      "game_id": "823612",
      "game_date": "2026-06-25",
      "away_team": "CHC",
      "home_team": "NYM",
      "away_team_name": "Chicago Cubs",
      "home_team_name": "New York Mets",
      "venue": null,
      "lineup_source": "confirmed_lineup",
      "away_lineup_source": "confirmed_lineup",
      "home_lineup_source": "confirmed_lineup",
      "probable_pitchers": {
        "away": {
          "slug": "matthew-boyd",
          "full_name": "Matthew Boyd",
          "team_abbr": null,
          "throws": null,
          "pitcher_foundation_signal": 56,
          "profile_type": "Volatile Arm",
          "confidence": "LOW",
          "k9": 11.62,
          "bb9": 2.25,
          "era": 6.0,
          "whip": 1.292
        },
        "home": {
          "slug": "freddy-peralta",
          "full_name": "Freddy Peralta",
          "team_abbr": "NYM",
          "throws": null,
          "pitcher_foundation_signal": 47,
          "profile_type": "Volatile Arm",
          "confidence": "HIGH",
          "k9": 9.12,
          "bb9": 3.69,
          "era": 4.04,
          "whip": 1.321
        }
      },
      "away_bats_to_watch": [
        {
          "slug": "pete-crow-armstrong",
          "full_name": "Pete Crow-Armstrong",
          "team_abbr": "CHC",
          "position": "CF",
          "bats": "L",
          "power_signal": 80,
          "contact_signal": 49,
          "luck_gap_points": 11,
          "hitter_profile_type": "Volatile Slugger",
          "confidence": "HIGH",
          "tags": [
            "Power Watch"
          ],
          "note": "Pete Crow-Armstrong brings strong power indicators."
        },
        {
          "slug": "ian-happ",
          "full_name": "Ian Happ",
          "team_abbr": "CHC",
          "position": "LF",
          "bats": "S",
          "power_signal": 81,
          "contact_signal": 44,
          "luck_gap_points": -21,
          "hitter_profile_type": "Volatile Slugger",
          "confidence": "HIGH",
          "tags": [
            "Power Watch"
          ],
          "note": "Ian Happ brings strong power indicators."
        }
      ],
      "home_bats_to_watch": [
        {
          "slug": "juan-soto",
          "full_name": "Juan Soto",
          "team_abbr": "NYM",
          "position": "LF",
          "bats": "L",
          "power_signal": 94,
          "contact_signal": 87,
          "luck_gap_points": 29,
          "hitter_profile_type": "Real Power Bat",
          "confidence": "HIGH",
          "tags": [
            "Power Watch",
            "Contact Edge",
            "DFS Watch"
          ],
          "note": "Juan Soto brings strong power indicators, and backed by a stable contact profile."
        },
        {
          "slug": "bo-bichette",
          "full_name": "Bo Bichette",
          "team_abbr": "NYM",
          "position": "3B",
          "bats": "R",
          "power_signal": 63,
          "contact_signal": 44,
          "luck_gap_points": 58,
          "hitter_profile_type": "Buy-Low Bat",
          "confidence": "HIGH",
          "tags": [
            "Buy-Low Bat",
            "DFS Watch"
          ],
          "note": "Bo Bichette expected production is running ahead of current results."
        },
        {
          "slug": "carson-benge",
          "full_name": "Carson Benge",
          "team_abbr": "NYM",
          "position": "RF",
          "bats": "L",
          "power_signal": 62,
          "contact_signal": 54,
          "luck_gap_points": 35,
          "hitter_profile_type": "Buy-Low Bat",
          "confidence": "HIGH",
          "tags": [
            "Buy-Low Bat",
            "DFS Watch"
          ],
          "note": "Carson Benge expected production is running ahead of current results."
        },
        {
          "slug": "mark-vientos",
          "full_name": "Mark Vientos",
          "team_abbr": "NYM",
          "position": "1B",
          "bats": "R",
          "power_signal": 63,
          "contact_signal": 22,
          "luck_gap_points": 44,
          "hitter_profile_type": "Buy-Low Bat",
          "confidence": "HIGH",
          "tags": [
            "Buy-Low Bat",
            "DFS Watch"
          ],
          "note": "Mark Vientos expected production is running ahead of current results."
        }
      ],
      "away_lineup_pressure": {
        "power_score": 80,
        "contact_score": 46,
        "profile": "Power-heavy pressure",
        "notes": []
      },
      "home_lineup_pressure": {
        "power_score": 70,
        "contact_score": 52,
        "profile": "Moderate lineup pressure",
        "notes": [
          "Multiple high-signal bats are clustered in this lineup: Juan Soto, Bo Bichette, Carson Benge."
        ]
      },
      "pitcher_edges": [
        {
          "pitcher_slug": "matthew-boyd",
          "pitcher_name": "Matthew Boyd",
          "team_abbr": null,
          "opponent_team": "NYM",
          "edge_type": "Small Sample",
          "confidence": "LOW",
          "pitcher_foundation_signal": 56,
          "pitcher_profile_type": "Volatile Arm",
          "k9": 11.62,
          "bb9": 2.25,
          "note": "Matthew Boyd does not have enough innings yet for a confident read."
        }
      ],
      "fantasy_watch": [
        "Power Watch: Pete Crow-Armstrong is a home run threat in today's matchup.",
        "Power Watch: Juan Soto is a home run threat in today's matchup.",
        "Buy-Low Bat: Bo Bichette has been better than his results show."
      ],
      "matchup_notes": [
        "Matthew Boyd (Volatile Arm) faces Freddy Peralta (Volatile Arm)."
      ]
    },
    {
      "game_id": "824747",
      "game_date": "2026-06-25",
      "away_team": "NYY",
      "home_team": "BOS",
      "away_team_name": "New York Yankees",
      "home_team_name": "Boston Red Sox",
      "venue": null,
      "lineup_source": "confirmed_lineup",
      "away_lineup_source": "confirmed_lineup",
      "home_lineup_source": "confirmed_lineup",
      "probable_pitchers": {
        "away": {
          "slug": "cam-schlittler",
          "full_name": "Cam Schlittler",
          "team_abbr": "NYY",
          "throws": null,
          "pitcher_foundation_signal": 89,
          "profile_type": "Ace Foundation",
          "confidence": "HIGH",
          "k9": 9.77,
          "bb9": 1.54,
          "era": 1.87,
          "whip": 0.866
        },
        "home": {
          "slug": "connelly-early",
          "full_name": "Connelly Early",
          "team_abbr": "BOS",
          "throws": null,
          "pitcher_foundation_signal": 54,
          "profile_type": "Volatile Arm",
          "confidence": "HIGH",
          "k9": 8.75,
          "bb9": 3.42,
          "era": 3.3,
          "whip": 1.225
        }
      },
      "away_bats_to_watch": [
        {
          "slug": "cody-bellinger",
          "full_name": "Cody Bellinger",
          "team_abbr": "NYY",
          "position": "LF",
          "bats": "L",
          "power_signal": 52,
          "contact_signal": 88,
          "luck_gap_points": 7,
          "hitter_profile_type": "Contact-First Bat",
          "confidence": "HIGH",
          "tags": [
            "Contact Edge",
            "DFS Watch"
          ],
          "note": "Cody Bellinger backed by a stable contact profile."
        },
        {
          "slug": "paul-goldschmidt",
          "full_name": "Paul Goldschmidt",
          "team_abbr": "NYY",
          "position": "1B",
          "bats": "R",
          "power_signal": 59,
          "contact_signal": 78,
          "luck_gap_points": -10,
          "hitter_profile_type": "Contact-First Bat",
          "confidence": "HIGH",
          "tags": [
            "Contact Edge"
          ],
          "note": "Paul Goldschmidt backed by a stable contact profile."
        },
        {
          "slug": "ben-rice",
          "full_name": "Ben Rice",
          "team_abbr": "NYY",
          "position": "1B",
          "bats": "L",
          "power_signal": 87,
          "contact_signal": 79,
          "luck_gap_points": -34,
          "hitter_profile_type": "Watch List",
          "confidence": "HIGH",
          "tags": [
            "Power Watch",
            "Contact Edge",
            "DFS Watch"
          ],
          "note": "Ben Rice brings strong power indicators, and backed by a stable contact profile."
        },
        {
          "slug": "austin-wells",
          "full_name": "Austin Wells",
          "team_abbr": "NYY",
          "position": "C",
          "bats": null,
          "power_signal": 40,
          "contact_signal": 24,
          "luck_gap_points": 55,
          "hitter_profile_type": "Watch List",
          "confidence": "HIGH",
          "tags": [
            "DFS Watch"
          ],
          "note": "Austin Wells expected production is running ahead of current results."
        }
      ],
      "home_bats_to_watch": [
        {
          "slug": "willson-contreras",
          "full_name": "Willson Contreras",
          "team_abbr": "BOS",
          "position": "1B",
          "bats": "R",
          "power_signal": 81,
          "contact_signal": 68,
          "luck_gap_points": -1,
          "hitter_profile_type": "Real Power Bat",
          "confidence": "HIGH",
          "tags": [
            "Power Watch"
          ],
          "note": "Willson Contreras brings strong power indicators."
        }
      ],
      "away_lineup_pressure": {
        "power_score": 60,
        "contact_score": 67,
        "profile": "Moderate lineup pressure",
        "notes": [
          "Multiple high-signal bats are clustered in this lineup: Cody Bellinger, Ben Rice, Austin Wells."
        ]
      },
      "home_lineup_pressure": {
        "power_score": 81,
        "contact_score": 68,
        "profile": "Heavy lineup pressure",
        "notes": []
      },
      "pitcher_edges": [
        {
          "pitcher_slug": "cam-schlittler",
          "pitcher_name": "Cam Schlittler",
          "team_abbr": "NYY",
          "opponent_team": "BOS",
          "edge_type": "Strikeout Upside",
          "confidence": "HIGH",
          "pitcher_foundation_signal": 89,
          "pitcher_profile_type": "Ace Foundation",
          "k9": 9.77,
          "bb9": 1.54,
          "note": "Cam Schlittler has strikeout upside against BOS."
        },
        {
          "pitcher_slug": "cam-schlittler",
          "pitcher_name": "Cam Schlittler",
          "team_abbr": "NYY",
          "opponent_team": "BOS",
          "edge_type": "Starting-Pitching Edge",
          "confidence": "HIGH",
          "pitcher_foundation_signal": 89,
          "pitcher_profile_type": "Ace Foundation",
          "k9": 9.77,
          "bb9": 1.54,
          "note": "Cam Schlittler gives his team the stronger starting-pitching edge in this matchup."
        }
      ],
      "fantasy_watch": [
        "Power Watch: Ben Rice is a home run threat in today's matchup.",
        "Power Watch: Willson Contreras is a home run threat in today's matchup.",
        "Strikeout Upside: Cam Schlittler has strikeout upside today.",
        "Risk Spot: Heavy lineup pressure lineup faces a tough matchup in Cam Schlittler."
      ],
      "matchup_notes": [
        "Cam Schlittler (Ace Foundation) faces Connelly Early (Volatile Arm)."
      ]
    },
    {
      "game_id": "823042",
      "game_date": "2026-06-25",
      "away_team": "AZ",
      "home_team": "STL",
      "away_team_name": "Arizona Diamondbacks",
      "home_team_name": "St. Louis Cardinals",
      "venue": null,
      "lineup_source": "confirmed_lineup",
      "away_lineup_source": "confirmed_lineup",
      "home_lineup_source": "confirmed_lineup",
      "probable_pitchers": {
        "away": {
          "slug": "zac-gallen",
          "full_name": "Zac Gallen",
          "team_abbr": "ARI",
          "throws": null,
          "pitcher_foundation_signal": 23,
          "profile_type": "Pitching Risk",
          "confidence": "HIGH",
          "k9": 5.94,
          "bb9": 2.71,
          "era": 5.43,
          "whip": 1.55
        },
        "home": {
          "slug": "michael-mcgreevy",
          "full_name": "Michael McGreevy",
          "team_abbr": "STL",
          "throws": null,
          "pitcher_foundation_signal": 58,
          "profile_type": "Volatile Arm",
          "confidence": "HIGH",
          "k9": 6.1,
          "bb9": 2.12,
          "era": 2.99,
          "whip": 1.078
        }
      },
      "away_bats_to_watch": [
        {
          "slug": "ketel-marte",
          "full_name": "Ketel Marte",
          "team_abbr": "ARI",
          "position": "2B",
          "bats": "S",
          "power_signal": 77,
          "contact_signal": 61,
          "luck_gap_points": 46,
          "hitter_profile_type": "Buy-Low Bat",
          "confidence": "HIGH",
          "tags": [
            "Power Watch",
            "Buy-Low Bat",
            "DFS Watch"
          ],
          "note": "Ketel Marte brings strong power indicators, and expected production is running ahead of current results."
        },
        {
          "slug": "corbin-carroll",
          "full_name": "Corbin Carroll",
          "team_abbr": "ARI",
          "position": "RF",
          "bats": "L",
          "power_signal": 83,
          "contact_signal": 75,
          "luck_gap_points": -29,
          "hitter_profile_type": "Real Power Bat",
          "confidence": "HIGH",
          "tags": [
            "Power Watch",
            "Contact Edge"
          ],
          "note": "Corbin Carroll brings strong power indicators, and backed by a stable contact profile."
        }
      ],
      "home_bats_to_watch": [
        {
          "slug": "alec-burleson",
          "full_name": "Alec Burleson",
          "team_abbr": "STL",
          "position": "1B",
          "bats": "L",
          "power_signal": 78,
          "contact_signal": 79,
          "luck_gap_points": 22,
          "hitter_profile_type": "Real Power Bat",
          "confidence": "HIGH",
          "tags": [
            "Power Watch",
            "Contact Edge"
          ],
          "note": "Alec Burleson brings strong power indicators, and backed by a stable contact profile."
        },
        {
          "slug": "jordan-walker",
          "full_name": "Jordan Walker",
          "team_abbr": "STL",
          "position": "RF",
          "bats": "R",
          "power_signal": 92,
          "contact_signal": 66,
          "luck_gap_points": -26,
          "hitter_profile_type": "Real Power Bat",
          "confidence": "HIGH",
          "tags": [
            "Power Watch",
            "DFS Watch"
          ],
          "note": "Jordan Walker brings strong power indicators."
        },
        {
          "slug": "ivan-herrera",
          "full_name": "Iv\u00e1n Herrera",
          "team_abbr": "STL",
          "position": "DH",
          "bats": "R",
          "power_signal": 49,
          "contact_signal": 80,
          "luck_gap_points": 5,
          "hitter_profile_type": "Contact-First Bat",
          "confidence": "HIGH",
          "tags": [
            "Contact Edge"
          ],
          "note": "Iv\u00e1n Herrera backed by a stable contact profile."
        }
      ],
      "away_lineup_pressure": {
        "power_score": 80,
        "contact_score": 68,
        "profile": "Heavy lineup pressure",
        "notes": []
      },
      "home_lineup_pressure": {
        "power_score": 73,
        "contact_score": 75,
        "profile": "Contact-heavy pressure",
        "notes": []
      },
      "pitcher_edges": [
        {
          "pitcher_slug": "zac-gallen",
          "pitcher_name": "Zac Gallen",
          "team_abbr": "ARI",
          "opponent_team": "STL",
          "edge_type": "Pitcher Risk",
          "confidence": "HIGH",
          "pitcher_foundation_signal": 23,
          "pitcher_profile_type": "Pitching Risk",
          "k9": 5.94,
          "bb9": 2.71,
          "note": "Zac Gallen is a risky spot against STL."
        }
      ],
      "fantasy_watch": [
        "Power Watch: Ketel Marte is a home run threat in today's matchup.",
        "Power Watch: Alec Burleson is a home run threat in today's matchup.",
        "Risk Spot: Zac Gallen is a risky spot against STL.",
        "Buy-Low Bat: Ketel Marte has been better than his results show."
      ],
      "matchup_notes": [
        "Zac Gallen (Pitching Risk) faces Michael McGreevy (Volatile Arm)."
      ]
    }
  ]
}