{
  "updated": "2026-06-10 10:19",
  "season": 2026,
  "leagues": [
    {
      "league": "AL",
      "divisions": [
        {
          "name": "East",
          "teams": [
            {
              "city": "Tampa Bay",
              "w": 39,
              "l": 25,
              "gb": "-"
            },
            {
              "city": "New York",
              "w": 40,
              "l": 26,
              "gb": "-"
            },
            {
              "city": "Toronto",
              "w": 33,
              "l": 35,
              "gb": "8.0"
            },
            {
              "city": "Baltimore",
              "w": 31,
              "l": 37,
              "gb": "10.0"
            },
            {
              "city": "Boston",
              "w": 27,
              "l": 38,
              "gb": "12.5"
            }
          ]
        },
        {
          "name": "Central",
          "teams": [
            {
              "city": "Cleveland",
              "w": 37,
              "l": 32,
              "gb": "-"
            },
            {
              "city": "Chicago",
              "w": 35,
              "l": 31,
              "gb": "0.5"
            },
            {
              "city": "Minnesota",
              "w": 30,
              "l": 38,
              "gb": "6.5"
            },
            {
              "city": "Detroit",
              "w": 28,
              "l": 39,
              "gb": "8.0"
            },
            {
              "city": "Kansas City",
              "w": 28,
              "l": 39,
              "gb": "8.0"
            }
          ]
        },
        {
          "name": "West",
          "teams": [
            {
              "city": "Seattle",
              "w": 36,
              "l": 32,
              "gb": "-"
            },
            {
              "city": "Texas",
              "w": 32,
              "l": 34,
              "gb": "3.0"
            },
            {
              "city": "Athletics",
              "w": 32,
              "l": 35,
              "gb": "3.5"
            },
            {
              "city": "Houston",
              "w": 31,
              "l": 38,
              "gb": "5.5"
            },
            {
              "city": "Los Angeles",
              "w": 26,
              "l": 42,
              "gb": "10.0"
            }
          ]
        }
      ]
    },
    {
      "league": "NL",
      "divisions": [
        {
          "name": "East",
          "teams": [
            {
              "city": "Atlanta",
              "w": 45,
              "l": 22,
              "gb": "-"
            },
            {
              "city": "Philadelphia",
              "w": 36,
              "l": 31,
              "gb": "9.0"
            },
            {
              "city": "Washington",
              "w": 35,
              "l": 33,
              "gb": "10.5"
            },
            {
              "city": "Miami",
              "w": 32,
              "l": 35,
              "gb": "13.0"
            },
            {
              "city": "New York",
              "w": 29,
              "l": 37,
              "gb": "15.5"
            }
          ]
        },
        {
          "name": "Central",
          "teams": [
            {
              "city": "Milwaukee",
              "w": 41,
              "l": 24,
              "gb": "-"
            },
            {
              "city": "St. Louis",
              "w": 36,
              "l": 28,
              "gb": "4.5"
            },
            {
              "city": "Pittsburgh",
              "w": 34,
              "l": 33,
              "gb": "8.0"
            },
            {
              "city": "Chicago",
              "w": 34,
              "l": 33,
              "gb": "8.0"
            },
            {
              "city": "Cincinnati",
              "w": 32,
              "l": 34,
              "gb": "9.5"
            }
          ]
        },
        {
          "name": "West",
          "teams": [
            {
              "city": "Los Angeles",
              "w": 43,
              "l": 24,
              "gb": "-"
            },
            {
              "city": "Arizona",
              "w": 34,
              "l": 32,
              "gb": "8.5"
            },
            {
              "city": "San Diego",
              "w": 34,
              "l": 32,
              "gb": "8.5"
            },
            {
              "city": "San Francisco",
              "w": 27,
              "l": 41,
              "gb": "16.5"
            },
            {
              "city": "Colorado",
              "w": 25,
              "l": 42,
              "gb": "18.0"
            }
          ]
        }
      ]
    }
  ]
}